latentmetrics/__init__.py
latentmetrics/api.py
latentmetrics/registry.py
latentmetrics/types.py
latentmetrics/engines/rank_based.py
latentmetrics/engines/utils.py
latentmetrics/engines/value_based.py
latentmetrics-0.1.0.dist-info/licenses/LICENSE
latentmetrics-0.1.0.dist-info/METADATA
latentmetrics-0.1.0.dist-info/WHEEL
latentmetrics-0.1.0.dist-info/top_level.txt
latentmetrics-0.1.0.dist-info/RECORD
