Metadata-Version: 2.4
Name: latentmetrics
Version: 0.1.0
Summary: Minimalistic latent correlation estimators for discretized data.
Author-email: Pavel Novikov <pavnoval@gmail.com>
License: MIT
Requires-Python: >=3.11
License-File: LICENSE
Requires-Dist: numpy>=1.25.2
Requires-Dist: scipy>=1.16.3
Provides-Extra: test
Requires-Dist: pytest>=7.0; extra == "test"
Requires-Dist: pytest-cov>=4.0; extra == "test"
Provides-Extra: dev
Requires-Dist: black; extra == "dev"
Requires-Dist: flake8; extra == "dev"
Dynamic: license-file
